Metadata-Version: 1.0
Name: selwyn-binomial
Version: 0.2
Summary: package to calculate and visualise binomial distribution
Home-page: UNKNOWN
Author: rlimbu
Author-email: noreply@gmail.com
License: UNKNOWN
Platform: UNKNOWN
